SUWWP/__init__.py
SUWWP/f_directories/structure_project.py
SUWWP/f_files/file_read.py
SUWWP/f_files/find_file_by_extension.py
SUWWP/f_files/write_file.py
SUWWP/f_randoms/random_copy.py
SUWWP/f_time/time_now.py
suwwp-0.2.5.dist-info/licenses/AUTHORS.md
suwwp-0.2.5.dist-info/licenses/LICENSE
suwwp-0.2.5.dist-info/METADATA
suwwp-0.2.5.dist-info/WHEEL
suwwp-0.2.5.dist-info/top_level.txt
suwwp-0.2.5.dist-info/RECORD
