Metadata-Version: 2.4
Name: SUWWP
Version: 0.2.5
Summary: Speeding Up Work With Python
Author-email: Dovintc <dovintc23@gmail.com>, Tooch1c <d18044204@gmail.com>
License-Expression: MIT
Project-URL: Homepage, https://github.com/Dovintc32/SUWWP 
Project-URL: Repository, https://github.com/Dovintc32/SUWWP 
Project-URL: License, https://github.com/Dovintc32/SUWWP?tab=MIT-1-ov-file#readme
Keywords: python,utility,helper,suwwp,speedup,development
Classifier: Development Status :: 3 - Alpha
Classifier: Intended Audience :: Developers
Classifier: Topic :: Software Development :: Libraries :: Python Modules
Classifier: Topic :: Utilities
Classifier: Programming Language :: Python :: 3
Classifier: Programming Language :: Python :: 3.6
Classifier: Programming Language :: Python :: 3.7
Classifier: Programming Language :: Python :: 3.8
Classifier: Programming Language :: Python :: 3.9
Classifier: Programming Language :: Python :: 3.10
Classifier: Programming Language :: Python :: 3.11
Classifier: Programming Language :: Python :: 3.12
Classifier: Operating System :: OS Independent
Requires-Python: >=3.6
License-File: LICENSE
License-File: AUTHORS.md
Dynamic: license-file
